cmeasures
