Metadata-Version: 1.0
Name: cmeasures
Version: 0.2
Summary: Centrality Measures
Home-page: UNKNOWN
Author: UNKNOWN
Author-email: buba222@list.ru
License: UNKNOWN
Platform: UNKNOWN
